Metadata-Version: 1.0
Name: kaddle
Version: 0.0.0
Summary: kaddle
Home-page: https://github.com/bojone/bert4keras
Author: bojone
Author-email: bojone@spaces.ac.cn
License: Apache License 2.0
Platform: UNKNOWN
